deltaray/__init__.py
deltaray/data/__init__.py
deltaray/data/read_api.py
deltaray-0.2.0.dist-info/LICENSE
deltaray-0.2.0.dist-info/METADATA
deltaray-0.2.0.dist-info/WHEEL
deltaray-0.2.0.dist-info/top_level.txt
deltaray-0.2.0.dist-info/RECORD
