Metadata-Version: 2.1
Name: deltaray
Version: 0.2.0
Summary: Delta reader for the Ray open-source toolkit for building ML applications
Home-page: https://github.com/delta-incubator/deltaray.git
Author: James Hibbard
License: Apache License
Classifier: Programming Language :: Python :: 3
Classifier: License :: OSI Approved :: Apache Software License
Requires-Python: >=3.9
License-File: LICENSE
Requires-Dist: deltalake (>=0.7.0)
Requires-Dist: ray[data] (>=2.2.0)
Requires-Dist: numpy (>=1.24.1)
